promptcap/__init__.py
promptcap/configuration_ofa.py
promptcap/modeling_ofa.py
promptcap/promptcap.py
promptcap/resnet.py
promptcap/tokenization_ofa.py
promptcap/tokenization_ofa_fast.py
promptcap-1.0.2.dist-info/METADATA
promptcap-1.0.2.dist-info/WHEEL
promptcap-1.0.2.dist-info/top_level.txt
promptcap-1.0.2.dist-info/RECORD
