Metadata-Version: 2.1
Name: promptcap
Version: 1.0.2
Summary: Instruction-Guided Image Captioning
Home-page: https://github.com/yushihu/PromptCap
Author: Yushi Hu
Author-email: yushihu@uw.edu
License: MIT
Keywords: image captioning,image-to-text,instruction,natural language processing,computer vision
